{
  "IsRegenerate": false,
  "MenuPosition": "main",
  "RelativeNamespace": "Constants",
  "EntityName": "Currency",
  "EntityNamePlural": "Currencies",
  "TableName": "Currencies",
  "PrimaryKeyType": "int",
  "BaseClass": "Entity",
  "EntityHistory": false,
  "AutoMigration": true,
  "UpdateDatabase": true,
  "CreateUserInterface": true,
  "CreateViewOnly": true,
  "CreateExcelExport": true,
  "IsNonModalCRUDPage": false,
  "IsMasterDetailPage": false,
  "PagePermission": {
    "Host": false,
    "Tenant": false
  },
  "Properties": [
    {
      "Name": "Code",
      "Type": "string",
      "MaxLength": 10,
      "MinLength": 1,
      "Range": {
        "IsRangeSet": false,
        "MinimumValue": 0.0,
        "MaximumValue": 0.0
      },
      "Required": true,
      "Nullable": false,
      "Regex": "",
      "UserInterface": {
        "AdvancedFilter": true,
        "List": true,
        "CreateOrUpdate": true
      },
      "ViewType": null,
      "AdditionalData": {}
    },
    {
      "Name": "Symbol",
      "Type": "string",
      "MaxLength": 5,
      "MinLength": 1,
      "Range": {
        "IsRangeSet": false,
        "MinimumValue": 0.0,
        "MaximumValue": 0.0
      },
      "Required": true,
      "Nullable": false,
      "Regex": "",
      "UserInterface": {
        "AdvancedFilter": true,
        "List": true,
        "CreateOrUpdate": true
      },
      "ViewType": null,
      "AdditionalData": {}
    },
    {
      "Name": "OrderNumber",
      "Type": "int",
      "MaxLength": 0,
      "MinLength": 0,
      "Range": {
        "IsRangeSet": false,
        "MinimumValue": 0.0,
        "MaximumValue": 0.0
      },
      "Required": false,
      "Nullable": false,
      "Regex": "",
      "UserInterface": {
        "AdvancedFilter": true,
        "List": true,
        "CreateOrUpdate": true
      },
      "ViewType": null,
      "AdditionalData": {}
    },
    {
      "Name": "NumberCode",
      "Type": "int",
      "MaxLength": 0,
      "MinLength": 0,
      "Range": {
        "IsRangeSet": false,
        "MinimumValue": 0.0,
        "MaximumValue": 0.0
      },
      "Required": false,
      "Nullable": false,
      "Regex": "",
      "UserInterface": {
        "AdvancedFilter": true,
        "List": true,
        "CreateOrUpdate": true
      },
      "ViewType": null,
      "AdditionalData": {}
    },
    {
      "Name": "IsActive",
      "Type": "bool",
      "MaxLength": 0,
      "MinLength": 0,
      "Range": {
        "IsRangeSet": false,
        "MinimumValue": 0.0,
        "MaximumValue": 0.0
      },
      "Required": false,
      "Nullable": false,
      "Regex": "",
      "UserInterface": {
        "AdvancedFilter": true,
        "List": true,
        "CreateOrUpdate": true
      },
      "ViewType": null,
      "AdditionalData": {}
    }
  ],
  "NavigationProperties": [],
  "NavigationPropertyOneToManyTables": [],
  "EnumDefinitions": [],
  "DbContext": null
}